pywow-1.0.dist-info/DESCRIPTION.rst
pywow-1.0.dist-info/METADATA
pywow-1.0.dist-info/RECORD
pywow-1.0.dist-info/WHEEL
pywow-1.0.dist-info/metadata.json
pywow-1.0.dist-info/top_level.txt
wow/__init__.py
