Metadata-Version: 2.0
Name: pywow
Version: 1.0
Summary: Python WoW API Wrapper
Home-page: https://github.com/mostm/pywow
Author: mostm
Author-email: mostm@endcape.ru
License: MIT
Keywords: wow world of warcraft world_of_warcraft python api wrapper lib
Platform: UNKNOWN
Classifier: Development Status :: 5 - Production/Stable
Classifier: Intended Audience :: Developers
Classifier: License :: OSI Approved :: MIT License
Classifier: Programming Language :: Python :: 3.5
Classifier: Programming Language :: Python :: 3.6
Requires-Dist: requests (<3,>=2.15)
Requires-Dist: Pillow (<5,>=4)
